{"variables":[],"info":{"name":"","_postman_id":"5aa208ff-45b0-4d32-9e96-9ad71fcf7ac6","description":"","schema":"https:\/\/schema.getpostman.com\/json\/collection\/v2.0.0\/collection.json"},"item":[{"name":"general","description":"","item":[{"name":"http:\/\/localhost\/v1\/login","request":{"url":"http:\/\/localhost\/v1\/login","method":"POST","body":{"mode":"formdata","formdata":[]},"description":"","response":[]}},{"name":"http:\/\/localhost\/v1\/register","request":{"url":"http:\/\/localhost\/v1\/register","method":"POST","body":{"mode":"formdata","formdata":[]},"description":"","response":[]}},{"name":"http:\/\/localhost\/v1\/health","request":{"url":"http:\/\/localhost\/v1\/health","method":"GET","body":{"mode":"formdata","formdata":[]},"description":"","response":[]}},{"name":"http:\/\/localhost\/v1\/links","request":{"url":"http:\/\/localhost\/v1\/links","method":"GET","body":{"mode":"formdata","formdata":[]},"description":"","response":[]}},{"name":"http:\/\/localhost\/v1\/links","request":{"url":"http:\/\/localhost\/v1\/links","method":"POST","body":{"mode":"formdata","formdata":[]},"description":"","response":[]}},{"name":"http:\/\/localhost\/v1\/links\/{link}","request":{"url":"http:\/\/localhost\/v1\/links\/{link}","method":"GET","body":{"mode":"formdata","formdata":[]},"description":"","response":[]}},{"name":"http:\/\/localhost\/v1\/links\/{link}","request":{"url":"http:\/\/localhost\/v1\/links\/{link}","method":"PUT","body":{"mode":"formdata","formdata":[]},"description":"","response":[]}},{"name":"http:\/\/localhost\/v1\/links\/{link}","request":{"url":"http:\/\/localhost\/v1\/links\/{link}","method":"DELETE","body":{"mode":"formdata","formdata":[]},"description":"","response":[]}},{"name":"http:\/\/localhost\/v1\/links\/{id}\/clicks","request":{"url":"http:\/\/localhost\/v1\/links\/{id}\/clicks","method":"GET","body":{"mode":"formdata","formdata":[]},"description":"","response":[]}},{"name":"http:\/\/localhost\/v1\/links\/{id}\/referrers","request":{"url":"http:\/\/localhost\/v1\/links\/{id}\/referrers","method":"GET","body":{"mode":"formdata","formdata":[]},"description":"","response":[]}},{"name":"http:\/\/localhost\/v1\/me","request":{"url":"http:\/\/localhost\/v1\/me","method":"GET","body":{"mode":"formdata","formdata":[]},"description":"","response":[]}}]}]}